LICENSE
README.md
setup.cfg
setup.py
gquant/__init__.py
gquant/_common.py
gquant/flow.py
gquant.egg-info/PKG-INFO
gquant.egg-info/SOURCES.txt
gquant.egg-info/dependency_links.txt
gquant.egg-info/entry_points.txt
gquant.egg-info/requires.txt
gquant.egg-info/top_level.txt
gquant/dataframe_flow/__init__.py
gquant/dataframe_flow/_node.py
gquant/dataframe_flow/_node_flow.py
gquant/dataframe_flow/cache.py
gquant/dataframe_flow/node.py
gquant/dataframe_flow/portsSpecSchema.py
gquant/dataframe_flow/task.py
gquant/dataframe_flow/taskGraph.py
gquant/dataframe_flow/taskSpecSchema.py
gquant/dataframe_flow/util.py
gquant/plugin_nodes/__init__.py
gquant/plugin_nodes/util/__init__.py
gquant/plugin_nodes/util/compositeNode.py
gquant/plugin_nodes/util/contextCompositeNode.py
gquant/plugin_nodes/util/data_obj.py
gquant/plugin_nodes/util/json_util.py