Metadata-Version: 2.1
Name: gquant
Version: 1.0.2
Summary: gquant - RAPIDS Financial Services Algorithms
Home-page: https://github.com/rapidsai/gQuant
Author: NVIDIA Corporation
License: Apache
Platform: UNKNOWN
Classifier: Development Status :: 4 - Beta
Classifier: Intended Audience :: Developers
Classifier: Intended Audience :: Science/Research
Classifier: Programming Language :: Python :: 3
Classifier: Operating System :: POSIX :: Linux
